README.md
setup.py
tproc.py
tproc.egg-info/PKG-INFO
tproc.egg-info/SOURCES.txt
tproc.egg-info/dependency_links.txt
tproc.egg-info/entry_points.txt
tproc.egg-info/requires.txt
tproc.egg-info/top_level.txt